[
  {
    "id": 1,
    "名称": "计算机系统基础",
    "教师": "陈锋",
    "星期": 0,
    "节次": 3,
    "时长": 3,
    "地点": 18
  },
  {
    "id": 2,
    "名称": "数据结构",
    "教师": "郜濒",
    "星期": 1,
    "节次": 2,
    "时长": 2,
    "地点": 18
  },
  {
    "id": 3,
    "名称": "离散数学",
    "教师": "珠峰",
    "星期": 2,
    "节次": 3,
    "时长": 3,
    "地点": 18
  },
  {
    "id": 4,
    "名称": "习近平新时代中国特色社会主义思想概论",
    "教师": "郭斌",
    "星期": 3,
    "节次": 1,
    "时长": 2,
    "地点": 19
  },
  {
    "id": 5,
    "名称": "概率论",
    "教师": "吴岗",
    "星期": 4,
    "节次": 2,
    "时长": 2,
    "地点": 18
  },
  {
    "id": 6,
    "名称": "电子学",
    "教师": "周智",
    "星期": 0,
    "节次": 6,
    "时长": 2,
    "地点": 2
  },
  {
    "id": 7,
    "名称": "高等数学",
    "教师": "陈锋",
    "星期": 1,
    "节次": 3,
    "时长": 2,
    "地点": 11
  },
  {
    "id": 8,
    "名称": "英语",
    "教师": "珠峰",
    "星期": 2,
    "节次": 7,
    "时长": 2,
    "地点": 11
  },
  {
    "id": 9,
    "名称": "中国近代史",
    "教师": "郭斌",
    "星期": 3,
    "节次": 7,
    "时长": 2,
    "地点": 19
  },
  {
    "id": 10,
    "名称": "军事理论",
    "教师": "吴岗",
    "星期": 4,
    "节次": 6,
    "时长": 3,
    "地点": 2
  }
]